docs/api/README.md
docs/api/chamfer_rsolid.md
docs/api/cut_rsolid.md
docs/api/export_step.md
docs/api/export_stl.md
docs/api/extrude_rsolid.md
docs/api/fillet_rsolid.md
docs/api/helical_sweep_rsolid.md
docs/api/intersect_rsolid.md
docs/api/linear_pattern_rsolidlist.md
docs/api/loft_rsolid.md
docs/api/make_angle_arc_redge.md
docs/api/make_angle_arc_rwire.md
docs/api/make_box_rsolid.md
docs/api/make_circle_redge.md
docs/api/make_circle_rface.md
docs/api/make_circle_rwire.md
docs/api/make_cone_rsolid.md
docs/api/make_cylinder_rsolid.md
docs/api/make_face_from_wire_rface.md
docs/api/make_helix_redge.md
docs/api/make_helix_rwire.md
docs/api/make_line_redge.md
docs/api/make_n_hole_flange_rsolid.md
docs/api/make_naca_propeller_blade_rsolid.md
docs/api/make_point_rvertex.md
docs/api/make_polyline_rwire.md
docs/api/make_rectangle_rface.md
docs/api/make_rectangle_rwire.md
docs/api/make_segment_redge.md
docs/api/make_segment_rwire.md
docs/api/make_sphere_rsolid.md
docs/api/make_spline_redge.md
docs/api/make_spline_rwire.md
docs/api/make_threaded_rod_rsolid.md
docs/api/make_three_point_arc_redge.md
docs/api/make_three_point_arc_rwire.md
docs/api/make_wire_from_edges_rwire.md
docs/api/mirror_shape.md
docs/api/radial_pattern_rsolidlist.md
docs/api/revolve_rsolid.md
docs/api/rotate_shape.md
docs/api/select_edges_by_tag.md
docs/api/select_faces_by_tag.md
docs/api/set_tag.md
docs/api/shell_rsolid.md
docs/api/sweep_rsolid.md
docs/api/translate_shape.md
docs/api/union_rsolid.md
docs/core/README.md
docs/core/compound.md
docs/core/coordinate_system.md
docs/core/edge.md
docs/core/face.md
docs/core/shell.md
docs/core/simple_workplane.md
docs/core/solid.md
docs/core/tagged_mixin.md
docs/core/vertex.md
docs/core/wire.md
simplecadapi/__init__.py
simplecadapi/__init__.py.bak
simplecadapi/core.py
simplecadapi/evolve.py
simplecadapi/operations.py
simplecadapi/py.typed
simplecadapi/auto_tools/README_ragflow_sync.md
simplecadapi/auto_tools/__init__.py
simplecadapi/auto_tools/auto_docs_gen.py
simplecadapi-1.1.2.1.dist-info/METADATA
simplecadapi-1.1.2.1.dist-info/WHEEL
simplecadapi-1.1.2.1.dist-info/entry_points.txt
simplecadapi-1.1.2.1.dist-info/licenses/LICENSE
simplecadapi-1.1.2.1.dist-info/RECORD
