Metadata-Version: 2.4
Name: simplecadapi
Version: 1.1.2.1
Summary: A simplified CAD modeling Python API based on CADQuery
Project-URL: Homepage, https://github.com/NiJingzhe/SimpleCADAPI
Project-URL: Repository, https://github.com/NiJingzhe/SimpleCADAPI
Project-URL: Documentation, https://github.com/NiJingzhe/SimpleCADAPI#readme
Project-URL: Issues, https://github.com/NiJingzhe/SimpleCADAPI/issues
Author-email: 倪旌哲 <nijingzhe@zju.edu.cn>
Maintainer-email: 倪旌哲 <nijingzhe@zju.edu.cn>
License:                     GNU GENERAL PUBLIC LICENSE
License-File: LICENSE
Keywords: 3d,cad,cadquery,design,modeling
Classifier: Development Status :: 3 - Alpha
Classifier: Intended Audience :: Developers
Classifier: Intended Audience :: Manufacturing
Classifier: License :: OSI Approved :: MIT License
Classifier: Operating System :: OS Independent
Classifier: Programming Language :: Python :: 3
Classifier: Programming Language :: Python :: 3.10
Classifier: Programming Language :: Python :: 3.11
Classifier: Programming Language :: Python :: 3.12
Classifier: Topic :: Scientific/Engineering
Classifier: Topic :: Scientific/Engineering :: Visualization
Requires-Python: >=3.10
Requires-Dist: cadquery>=2.5.2
Requires-Dist: numpy>=1.21.0
Requires-Dist: rich>=14.0.0
Provides-Extra: dev
Requires-Dist: black>=23.0; extra == 'dev'
Requires-Dist: isort>=5.0; extra == 'dev'
Requires-Dist: mypy>=1.0; extra == 'dev'
Requires-Dist: pytest-cov>=4.0; extra == 'dev'
Requires-Dist: pytest>=7.0; extra == 'dev'
Provides-Extra: editor
Requires-Dist: cq-editor>=0.5.0; extra == 'editor'
